laundryCode/__init__.py
laundryCode/hitungHarga.py
laundry_unit_testing-1.0.1.dist-info/LICENSE.txt
laundry_unit_testing-1.0.1.dist-info/METADATA
laundry_unit_testing-1.0.1.dist-info/WHEEL
laundry_unit_testing-1.0.1.dist-info/top_level.txt
laundry_unit_testing-1.0.1.dist-info/RECORD
