Metadata-Version: 2.1
Name: laundry_unit_testing
Version: 1.0.1
Summary: A simple laundry unit testing
Home-page: https://github.com/dlzcods/laundry-unit-testing
Author: Muhammad Abdiel Al Hafiz
Author-email: dielz032@gmail.com
Project-URL: repository, https://github.com/dlzcods/laundry-unit-testing
Classifier: Programming Language :: Python :: 3
Classifier: License :: OSI Approved :: MIT License
Classifier: Operating System :: OS Independent
Requires-Python: >=3.6
License-File: LICENSE.txt
